FileStandardInput
