Metadata-Version: 1.1
Name: FileStandardInput
Version: 0.2
Summary: A Python STDIN library to get input automatically from file
Home-page: www.github.com/ashik94vc/FileStandardInput
Author: Ashik Vetrivelu
Author-email: ashik@cepheuen.com
License: MIT
Keywords: file input fileinput standardinput
Platform: UNKNOWN
Classifier: Development Status :: 3 - Alpha
Classifier: Intended Audience :: Developers
Classifier: Topic :: Software Development :: Build Tools
Classifier: License :: OSI Approved :: MIT License
Classifier: Programming Language :: Python :: 2
Classifier: Programming Language :: Python :: 2.6
Classifier: Programming Language :: Python :: 2.7
Classifier: Programming Language :: Python :: 3
Classifier: Programming Language :: Python :: 3.2
Classifier: Programming Language :: Python :: 3.3
Classifier: Programming Language :: Python :: 3.4
